vocalpy/__about__.py
vocalpy/__init__.py
vocalpy/annotation.py
vocalpy/annotation_file.py
vocalpy/annotator.py
vocalpy/audio_file.py
vocalpy/constants.py
vocalpy/dataset_file.py
vocalpy/feature_extractor.py
vocalpy/feature_file.py
vocalpy/features.py
vocalpy/params.py
vocalpy/paths.py
vocalpy/segmenter.py
vocalpy/segments.py
vocalpy/sequence.py
vocalpy/sound.py
vocalpy/spectrogram.py
vocalpy/spectrogram_file.py
vocalpy/spectrogram_maker.py
vocalpy/spectrogram_parameters.py
vocalpy/unit.py
vocalpy/_spectrogram/__init__.py
vocalpy/_spectrogram/data_type.py
vocalpy/_vendor/__init__.py
vocalpy/_vendor/evfuncs.py
vocalpy/examples/BM003.wav
vocalpy/examples/BM003.wav.description.txt
vocalpy/examples/WhiLbl0010.description.txt
vocalpy/examples/WhiLbl0010_110411-DC-01.wav
vocalpy/examples/__init__.py
vocalpy/examples/_examples.py
vocalpy/examples/bells.wav
vocalpy/examples/bfsongrepo.description.txt
vocalpy/examples/bl26lb16.wav
vocalpy/examples/bl26lb16.wav.description.txt
vocalpy/examples/deermouse-go.wav
vocalpy/examples/deermouse-go.wav.description.txt
vocalpy/examples/example-metadata.json
vocalpy/examples/example_data.py
vocalpy/examples/flashcam.wav
vocalpy/examples/fruitfly-song-multichannel.wav
vocalpy/examples/fruitfly-song-multichannel.wav.description.txt
vocalpy/examples/samba.wav
vocalpy/examples/simple.wav
vocalpy/examples/twopup.description.txt
vocalpy/examples/zblib.description.txt
vocalpy/examples/zebra-finch-SAP.description.txt
vocalpy/feature/__init__.py
vocalpy/feature/_sat.py
vocalpy/feature/_biosound/__init__.py
vocalpy/feature/_biosound/constants.py
vocalpy/feature/_biosound/detect_peaks.py
vocalpy/feature/_biosound/features.py
vocalpy/feature/_biosound/fundamental.py
vocalpy/feature/_biosound/signal.py
vocalpy/feature/_biosound/sound.py
vocalpy/metrics/__init__.py
vocalpy/metrics/segmentation/__init__.py
vocalpy/metrics/segmentation/ir.py
vocalpy/plot/__init__.py
vocalpy/plot/annot.py
vocalpy/plot/spect.py
vocalpy/segment/__init__.py
vocalpy-0.10.3.post1.dist-info/licenses/LICENSE
vocalpy-0.10.3.post1.dist-info/WHEEL
vocalpy-0.10.3.post1.dist-info/METADATA
vocalpy-0.10.3.post1.dist-info/RECORD
