Metadata-Version: 2.4
Name: vocalpy
Version: 0.10.3.post1
Summary: A core package for acoustic communication research in Python
Author-email: David Nicholson <nickledave@users.noreply.github.com>
Requires-Python: >=3.12
Classifier: License :: OSI Approved :: BSD License
Classifier: Development Status :: 5 - Production/Stable
Classifier: Programming Language :: Python
Classifier: Programming Language :: Python :: 3
Classifier: Programming Language :: Python :: 3.12
Classifier: Programming Language :: Python :: 3.13
Classifier: Programming Language :: Python :: Implementation :: CPython
License-File: LICENSE
Requires-Dist: attrs >=25.3.0
Requires-Dist: crowsetta >=5.1.3
Requires-Dist: dask[dataframe] >=2025.5.1
Requires-Dist: h5netcdf >= 1.3.0
Requires-Dist: librosa >= 0.11.0
Requires-Dist: matplotlib >=3.9.0
Requires-Dist: numpy >=2.0.0
Requires-Dist: pandas >= 2.2.0
Requires-Dist: pooch >= 1.8.2
Requires-Dist: scipy >=1.12.0
Requires-Dist: SoundFile >=0.13.1
Requires-Dist: xarray >= 2023.11.0
Project-URL: Docs, https://vocalpy.readthedocs.io
Project-URL: Home, https://github.com/vocalpy/vocalpy
